ICS_VSBIO/ICSFileInterfaceLibrary.py
ICS_VSBIO/VSBIOFlags.py
ICS_VSBIO/VSBIOInterface.py
ICS_VSBIO/VSBReader.py
ICS_VSBIO/VSBWriter.py
ICS_VSBIO/_VSBIOFlags.cp310-win_amd64.pyd
ICS_VSBIO/_VSBIOInterface.cp310-win_amd64.pyd
ICS_VSBIO-1.5.5.dist-info/METADATA
ICS_VSBIO-1.5.5.dist-info/WHEEL
ICS_VSBIO-1.5.5.dist-info/top_level.txt
ICS_VSBIO-1.5.5.dist-info/RECORD
